{
  "id": 3,
  "category": "beginner-ba-duan-jin-follow-along",
  "theme": "Understanding Beginner Ba Duan Jin Follow Along",
  "tone": "academic",
  "title": "Beginner Ba Duan Jin Follow Along: Must-Read Insights and Reviews",
  "slug": "beginner-ba-duan-jin-follow-along-must-read-insights-and-reviews",
  "meta_description": "Explore the fascinating world of Understanding Beginner Ba Duan Jin Follow Along with our in-depth analysis. From beginner basics to advanced techniques, find everything you need to know.",
  "content": "Abstract: This paper examines the multi-faceted nature of Understanding Beginner Ba Duan Jin Follow Along. The world of Understanding Beginner Ba Duan Jin Follow Along is constantly evolving, and staying updated is crucial. In this comprehensive article, we'll cover the latest trends, best practices, and essential information you need to know. Whether you're a hobbyist or professional, you'll find valuable insights here.\n\n<h2>Getting Started</h2>\n<p>While simple on the surface, this has profound implications when applied.</p>\n<p>Ready to begin? Let's walk through the essential first steps you need to take. This practical guide will help you navigate the initial stages with confidence and set you up for success.</p>\n\n**Key Insight**: 45% reduction in common errors within two weeks  \n*Source: Quality Control Review*\n\n<h2>Advanced Techniques</h2>\n<p>For those looking to expand their expertise, this section dives into more advanced topics and techniques. These are the skills that will truly set you apart from the crowd. Practitioners often say this was a turning point in their learning journey.</p>\n\n<h2>Recommended Resources</h2>\n<p>Having the right tools makes all the difference. This section covers essential tools, resources, and materials that will help you on your journey and make your learning experience smoother.</p>\n\n<h2>Common Misconceptions</h2>\n<p>Misinformation can hold you back. In this section, we'll debunk common myths and misconceptions about this subject, helping you build your knowledge on a solid foundation of truth.</p>\n\n⚠️ **Important Note**: Don't rush the process—consistency yields far better results than intensity. Take your time to fully understand each concept before moving on.\n\n<h2>Origins and Evolution</h2>\n<p>From humble beginnings to widespread adoption, the story of how this subject developed is fascinating and informative. We trace its journey through time. This is one of the fundamental building blocks for future success.</p>\n\n<h2>Looking Ahead</h2>\n<p>Look ahead at emerging trends and developments in this field. Stay ahead of the curve by understanding where things are heading and how to prepare for what comes next in this exciting space.</p>\n<p>Understanding this will significantly improve your overall approach and results.</p>\n\n<h2>Expert Tips</h2>\n<p>What do the experts recommend? Let's look at proven strategies and best practices that have stood the test of time. Implementing these will help you achieve better results more efficiently.</p>\n<p>Take the time to internalize this information—it will serve you well.</p>\n<p>The more you practice this, the more natural it will become.</p>\n\n<h2>Options Explored</h2>\n<p>There are multiple ways to approach this topic, each with its own strengths. This section compares different methodologies to help you choose what works best for you.</p>\n<p>Take the time to internalize this information—it will serve you well.</p>\n<p>Learning is a journey, not a race—enjoy the process.</p>\n\n<h2>Expert Tips</h2>\n<p>Learn from those who have come before you. This section covers the proven strategies, techniques, and approaches that consistently deliver excellent results. These are the practices you'll want to adopt. This is a key concept that deserves your full attention and practice.</p>\n\n<h2>Comparative Analysis</h2>\n<p>Not every approach works for everyone. Here, we look at various strategies and discuss when to use which method for optimal results.</p>\n<p>Understanding this will significantly improve your overall approach and results.</p>\n\n<h2>Next Level</h2>\n<p>Understanding this will significantly improve your overall approach and results.</p>\n<p>Once you've mastered the fundamentals, what's next? Let's explore advanced techniques and strategies that will help you elevate your skills and knowledge to new heights.</p>\n\n<h2>Understanding Understanding Beginner Ba Duan Jin Follow Along</h2>\n<p>This is one of the fundamental building blocks for future success.</p>\n<p>Before we dive deeper, let's establish a clear understanding of what we're discussing. This section covers the essential definitions and basic principles that will guide us through the rest of the article. Take your time to absorb these key concepts.</p>\n\nAs we conclude this exploration of Understanding Beginner Ba Duan Jin Follow Along, remember that the most important thing is to apply what you've learned. Knowledge without action is just information. Take what you'discover here and put it into practice. You have the tools you need—now go make something amazing happen!",
  "created_at": "2026-06-05T17:13:07.562792",
  "word_count": 659,
  "seo": {
    "keywords": [
      "understanding beginner ba duan jin follow along",
      "beginner-ba-duan-jin-follow-along",
      "Understanding Beginner Ba Duan Jin Follow Along guide",
      "best Understanding Beginner Ba Duan Jin Follow Along",
      "Understanding Beginner Ba Duan Jin Follow Along tips",
      "Understanding Beginner Ba Duan Jin Follow Along 2026",
      "how to understanding beginner ba duan jin follow along"
    ],
    "title_tag": "Beginner Ba Duan Jin Follow Along: Must-Read Insights and Reviews | ba-duan-jin-follow-along",
    "meta_description": "Explore the fascinating world of Understanding Beginner Ba Duan Jin Follow Along with our in-depth analysis. From beginner basics to advanced techniques, find everything you need to know.",
    "og_title": "Beginner Ba Duan Jin Follow Along: Must-Read Insights and Reviews",
    "og_description": "Explore the fascinating world of Understanding Beginner Ba Duan Jin Follow Along with our in-depth analysis. From beginner basics to advanced techniques, find everything you need to know.",
    "og_type": "article",
    "twitter_card": "summary_large_image",
    "canonical_url": "/beginner-ba-duan-jin-follow-along-must-read-insights-and-reviews",
    "robots": "index, follow"
  },
  "geo": {
    "country": "France",
    "city": "Toulouse",
    "language": "en",
    "target_regions": [
      "North America",
      "Europe",
      "Asia Pacific"
    ]
  },
  "image": {
    "id": "693033ac4aadce65b90a327e22ace39a377b1fa1dd7d4624f32f2e3dcf23c64e",
    "url": "https://picsum.photos/805/490?random=810",
    "alt": "Featured image for: Beginner Ba Duan Jin Follow Along: Must-Read Insights and Reviews",
    "width": 805,
    "height": 490
  }
}